lucatele/__init__.py
lucatele/api.py
lucatele/delegate.py
lucatele/exception.py
lucatele/filtering.py
lucatele/hack.py
lucatele/helper.py
lucatele/loop.py
lucatele/namedtuple.py
lucatele/routing.py
lucatele/text.py
lucatele/aio/__init__.py
lucatele/aio/api.py
lucatele/aio/delegate.py
lucatele/aio/hack.py
lucatele/aio/helper.py
lucatele/aio/loop.py
lucatele/aio/routing.py
teleluc/__init__.py
teleluc/api.py
teleluc/delegate.py
teleluc/exception.py
teleluc/filtering.py
teleluc/hack.py
teleluc/helper.py
teleluc/loop.py
teleluc/namedtuple.py
teleluc/routing.py
teleluc/text.py
teleluc/aio/__init__.py
teleluc/aio/api.py
teleluc/aio/delegate.py
teleluc/aio/hack.py
teleluc/aio/helper.py
teleluc/aio/loop.py
teleluc/aio/routing.py
teleluca/__init__.py
teleluca/api.py
teleluca/delegate.py
teleluca/exception.py
teleluca/filtering.py
teleluca/hack.py
teleluca/helper.py
teleluca/loop.py
teleluca/namedtuple.py
teleluca/routing.py
teleluca/text.py
teleluca/aio/__init__.py
teleluca/aio/api.py
teleluca/aio/delegate.py
teleluca/aio/hack.py
teleluca/aio/helper.py
teleluca/aio/loop.py
teleluca/aio/routing.py
lucatele-12.7.dist-info/METADATA
lucatele-12.7.dist-info/WHEEL
lucatele-12.7.dist-info/top_level.txt
lucatele-12.7.dist-info/RECORD
