Metadata-Version: 2.1
Name: lucatele
Version: 12.7
Summary: Python framework for Telegram Bot API
Home-page: https://github.com/nickoala/lucatele
Author: Nick Lee
Author-email: lee1nick@yahoo.ca
License: MIT
Keywords: telegram bot api python wrapper
Classifier: Development Status :: 5 - Production/Stable
Classifier: Intended Audience :: Developers
Classifier: Topic :: Software Development :: Libraries :: Python Modules
Classifier: Topic :: Communications :: Chat
Classifier: License :: OSI Approved :: MIT License
Classifier: Programming Language :: Python :: 2.7
Classifier: Programming Language :: Python :: 3
Classifier: Programming Language :: Python :: 3.2
Classifier: Programming Language :: Python :: 3.3
Classifier: Programming Language :: Python :: 3.4
Classifier: Programming Language :: Python :: 3.5
Classifier: Programming Language :: Python :: 3.6
Requires-Dist: urllib3 >=1.9.1
Requires-Dist: aiohttp >=3.0.0
